{"releases":[{"version":"1.0.1","status":{"Ok":{"name":"NoRedInk/elm-string-conversions","datetime":"2018-12-05T02:23:13Z","checksum":"3e51688101dfd8757178b4f754c9cc629199582f","in_registry":true,"has_docs":true,"has_readme":true,"ci":[],"license":"BSD-3-Clause","summary":"Helpers to convert common types into a `String`.","elm_versions":["0.19.0"],"exposed_modules":["String.Conversions"],"direct_dependencies":{"elm/core":"1.0.0 <= v < 2.0.0","elm/http":"2.0.0 <= v < 3.0.0","elm/json":"1.0.0 <= v < 2.0.0","elm/time":"1.0.0 <= v < 2.0.0"}}}},{"version":"1.0.0","status":{"Ok":{"name":"NoRedInk/elm-string-conversions","datetime":"2018-09-12T21:35:41Z","checksum":"e5443b3f3e53c750b847365f43f10df0fa6e841c","in_registry":true,"has_docs":true,"has_readme":true,"ci":[],"license":"BSD-3-Clause","summary":"Helpers to convert common types into a `String`.","elm_versions":["0.19.0"],"exposed_modules":["String.Conversions"],"direct_dependencies":{"elm/core":"1.0.0 <= v < 2.0.0","elm/http":"1.0.0 <= v < 2.0.0","elm/json":"1.0.0 <= v < 2.0.0","elm/time":"1.0.0 <= v < 2.0.0"}}}}]}