{"releases":[{"version":"1.0.1","status":{"Ok":{"name":"fbonetti/elm-phoenix-socket","datetime":"2016-05-31T01:05:55Z","checksum":"44ea5b9ccb989f7cbf17ab0049a0e08041603fd1","in_registry":true,"has_docs":true,"has_readme":true,"ci":[],"license":"MIT","summary":"Pure Elm state manager for Phoenix channels","elm_versions":["0.17.1","0.17.0"],"direct_dependencies":{"elm-lang/core":"4.0.0 <= v < 5.0.0","elm-lang/html":"1.0.0 <= v < 2.0.0","elm-lang/websocket":"1.0.0 <= v < 2.0.0"}}}},{"version":"1.0.0","status":{"Ok":{"name":"fbonetti/elm-phoenix-socket","datetime":"2016-05-29T22:35:02Z","checksum":"0e3f7ebee50bc1e3c9a9a49f46c203ed52f66a6a","in_registry":false,"has_docs":true,"has_readme":true,"ci":[],"license":"MIT","summary":"Pure Elm state manager for Phoenix channels","elm_versions":["0.17.1","0.17.0"],"direct_dependencies":{"elm-lang/core":"4.0.0 <= v < 5.0.0","elm-lang/html":"1.0.0 <= v < 2.0.0","elm-lang/websocket":"1.0.0 <= v < 2.0.0"}}}}]}