{"releases":[{"version":"1.8.0","status":{"Ok":{"name":"mgold/elm-date-format","datetime":"2018-07-30T04:06:30Z","checksum":"2309b0eebbe5400f627bffd9943cb2b5ad2bd4e8","in_registry":true,"has_docs":true,"has_readme":true,"ci":[],"license":"BSD3","summary":"Format dates with ease","elm_versions":["0.18.0"],"direct_dependencies":{"elm-lang/core":"5.0.0 <= v < 6.0.0"}}}},{"version":"1.7.0","status":{"Ok":{"name":"mgold/elm-date-format","datetime":"2018-07-23T05:34:32Z","checksum":"eab05aefea55a05fad55a309c14d9e67f9314ed2","in_registry":true,"has_docs":true,"has_readme":true,"ci":[],"license":"BSD3","summary":"Format dates with ease","elm_versions":["0.18.0"],"direct_dependencies":{"elm-lang/core":"5.0.0 <= v < 6.0.0"}}}},{"version":"1.6.0","status":{"Ok":{"name":"mgold/elm-date-format","datetime":"2018-05-27T03:32:20Z","checksum":"1ce6df4c8e99dd417aee35415ee9c707b60cc732","in_registry":true,"has_docs":true,"has_readme":true,"ci":[],"license":"BSD3","summary":"Format dates with ease","elm_versions":["0.18.0"],"direct_dependencies":{"elm-lang/core":"5.0.0 <= v < 6.0.0"}}}},{"version":"1.5.0","status":{"Ok":{"name":"mgold/elm-date-format","datetime":"2018-02-09T06:18:14Z","checksum":"4aa6afe74160ca05732e6f4203b9fb1aba460ae8","in_registry":true,"has_docs":true,"has_readme":true,"ci":[],"license":"BSD3","summary":"Format dates with ease","elm_versions":["0.18.0"],"direct_dependencies":{"elm-lang/core":"5.0.0 <= v < 6.0.0"}}}},{"version":"1.4.2","status":{"Ok":{"name":"mgold/elm-date-format","datetime":"2017-11-19T19:15:00Z","checksum":"c97fa467438df3d026c3bf44f6a92977f425d4c4","in_registry":true,"has_docs":true,"has_readme":true,"ci":[],"license":"BSD3","summary":"Format dates with ease","elm_versions":["0.18.0"],"direct_dependencies":{"elm-lang/core":"5.0.0 <= v < 6.0.0"}}}},{"version":"1.4.1","status":{"Ok":{"name":"mgold/elm-date-format","datetime":"2017-10-10T01:51:54Z","checksum":"ff3ad9264fa9883b18eb60d43dabbd62fe1807f9","in_registry":true,"has_docs":true,"has_readme":true,"ci":[],"license":"BSD3","summary":"Format dates with ease","elm_versions":["0.18.0"],"direct_dependencies":{"elm-lang/core":"5.0.0 <= v < 6.0.0"}}}},{"version":"1.4.0","status":{"Ok":{"name":"mgold/elm-date-format","datetime":"2017-07-11T04:35:32Z","checksum":"ecbe1ea0cee365b3c23ea3102b0f803c39f20d84","in_registry":true,"has_docs":true,"has_readme":true,"ci":[],"license":"BSD3","summary":"Format dates with ease","elm_versions":["0.18.0"],"direct_dependencies":{"elm-lang/core":"5.0.0 <= v < 6.0.0"}}}},{"version":"1.3.0","status":{"Ok":{"name":"mgold/elm-date-format","datetime":"2017-04-05T01:13:31Z","checksum":"621760f0e2c916dad1db34273441c69d99e2f03c","in_registry":true,"has_docs":true,"has_readme":true,"ci":[],"license":"BSD3","summary":"Format dates with ease","elm_versions":["0.18.0"],"direct_dependencies":{"elm-lang/core":"5.0.0 <= v < 6.0.0"}}}},{"version":"1.2.0","status":{"Ok":{"name":"mgold/elm-date-format","datetime":"2017-02-07T05:40:24Z","checksum":"9f392b1783e8cf356d1e62fe84c4ca7f9dd348dd","in_registry":true,"has_docs":true,"has_readme":true,"ci":[],"license":"BSD3","summary":"Format dates with ease","elm_versions":["0.18.0"],"direct_dependencies":{"elm-lang/core":"5.0.0 <= v < 6.0.0"}}}},{"version":"1.1.7","status":{"Ok":{"name":"mgold/elm-date-format","datetime":"2016-11-15T15:57:21Z","checksum":"abd54fd76e012caeea42ae61c06167b16996d6fe","in_registry":true,"has_docs":true,"has_readme":true,"ci":[],"license":"BSD3","summary":"Format dates with ease","elm_versions":["0.18.0"],"direct_dependencies":{"elm-lang/core":"5.0.0 <= v < 6.0.0"}}}},{"version":"1.1.6","status":{"Ok":{"name":"mgold/elm-date-format","datetime":"2016-09-28T03:52:53Z","checksum":"b272979f2bd8e7585d64719a192e467bf4a47f55","in_registry":true,"has_docs":true,"has_readme":true,"ci":[],"license":"BSD3","summary":"Format dates with ease","elm_versions":["0.17.1","0.17.0"],"direct_dependencies":{"elm-lang/core":"4.0.0 <= v < 5.0.0"}}}},{"version":"1.1.5","status":{"Ok":{"name":"mgold/elm-date-format","datetime":"2016-09-14T01:42:03Z","checksum":"5308c944d259986638d5d6d912526d3de6685354","in_registry":true,"has_docs":true,"has_readme":true,"ci":[],"license":"BSD3","summary":"Format dates with ease","elm_versions":["0.17.1","0.17.0"],"direct_dependencies":{"elm-lang/core":"4.0.0 <= v < 5.0.0"}}}},{"version":"1.1.4","status":{"Ok":{"name":"mgold/elm-date-format","datetime":"2016-05-14T16:07:38Z","checksum":"c4083b64a48fa5031d34e2c48bb925e92a7fb07d","in_registry":true,"has_docs":true,"has_readme":true,"ci":[],"license":"BSD3","summary":"Format dates with ease","elm_versions":["0.17.1","0.17.0"],"direct_dependencies":{"elm-lang/core":"4.0.0 <= v < 5.0.0"}}}},{"version":"1.1.3","status":{"Ok":{"name":"mgold/elm-date-format","datetime":"2016-03-05T17:06:53Z","checksum":"bf256ddc2a75090704c2e86399e882da7c821624","in_registry":true,"has_docs":true,"has_readme":true,"ci":[],"license":"BSD3","summary":"Format dates with ease","elm_versions":["0.16.0"],"direct_dependencies":{"elm-lang/core":"3.0.0 <= v < 4.0.0"}}}},{"version":"1.1.2","status":{"Ok":{"name":"mgold/elm-date-format","datetime":"2016-01-11T04:06:24Z","checksum":"6663ae98119312d48e315b8f92208474c13ab3c6","in_registry":true,"has_docs":true,"has_readme":true,"ci":[],"license":"BSD3","summary":"Format dates with ease","elm_versions":["0.16.0"],"direct_dependencies":{"elm-lang/core":"3.0.0 <= v < 4.0.0"}}}},{"version":"1.1.1","status":{"Ok":{"name":"mgold/elm-date-format","datetime":"2016-01-10T19:31:10Z","checksum":"418b847ee5f17cbe00cc2730a3c5b7251b0218dd","in_registry":true,"has_docs":true,"has_readme":true,"ci":[],"license":"BSD3","summary":"Format dates with ease","elm_versions":["0.16.0"],"direct_dependencies":{"elm-lang/core":"3.0.0 <= v < 4.0.0"}}}},{"version":"1.1.0","status":{"Ok":{"name":"mgold/elm-date-format","datetime":"2016-01-06T17:31:12Z","checksum":"7606174a644ae5d8eca3d18e08f82f8670e12947","in_registry":true,"has_docs":true,"has_readme":true,"ci":[],"license":"BSD3","summary":"Format dates with ease","elm_versions":["0.16.0"],"direct_dependencies":{"elm-lang/core":"3.0.0 <= v < 4.0.0"}}}},{"version":"1.0.4","status":{"Ok":{"name":"mgold/elm-date-format","datetime":"2015-12-12T02:50:14Z","checksum":"857abe78a3f59fcd97ea822e13fed9f7086b497d","in_registry":true,"has_docs":true,"has_readme":true,"ci":[],"license":"BSD3","summary":"Format dates with ease","elm_versions":["0.16.0"],"direct_dependencies":{"elm-lang/core":"3.0.0 <= v < 4.0.0"}}}},{"version":"1.0.3","status":{"Ok":{"name":"mgold/elm-date-format","datetime":"2015-12-01T00:06:07Z","checksum":"7570e21d206d570aca0a09d192fb3a20929ce1a4","in_registry":true,"has_docs":true,"has_readme":true,"ci":[],"license":"BSD3","summary":"Format dates with ease","elm_versions":["0.16.0"],"direct_dependencies":{"elm-lang/core":"3.0.0 <= v < 4.0.0"}}}},{"version":"1.0.2","status":{"Ok":{"name":"mgold/elm-date-format","datetime":"2015-11-22T17:40:09Z","checksum":"4bf229bd75e77cea16527fe58342d6a1f40f46e2","in_registry":true,"has_docs":true,"has_readme":true,"ci":[],"license":"BSD3","summary":"Format dates with ease","elm_versions":["0.16.0"],"direct_dependencies":{"deadfoxygrandpa/elm-test":"3.0.0 <= v < 4.0.0","elm-lang/core":"3.0.0 <= v < 4.0.0"}}}},{"version":"1.0.1","status":{"Ok":{"name":"mgold/elm-date-format","datetime":"2015-06-06T13:39:21Z","checksum":"d6b593e8fd107fd02915327fd90cffe130969630","in_registry":true,"has_docs":true,"has_readme":true,"ci":[],"license":"BSD3","summary":"Format dates with ease","elm_versions":["0.15.1","0.15.0"],"direct_dependencies":{"deadfoxygrandpa/Elm-Test":"1.0.3 <= v < 2.0.0","elm-lang/core":"2.0.0 <= v < 3.0.0"}}}},{"version":"1.0.0","status":{"Broken":{"name":null,"problems":["No valid `elm-package.json` or `elm.json`"],"datetime":"2014-12-13T18:19:16Z","checksum":"ff685891642740797a931a72233339731c286dc1","in_registry":null,"has_docs":false,"has_readme":false,"ci":null,"license":null,"summary":null,"elm_versions":null,"direct_dependencies":null}}}]}