{"releases":[{"version":"4.0.1","status":{"Ok":{"name":"labzero/elm-google-geocoding","datetime":"2016-11-14T22:24:42Z","checksum":"16099b9ed8fa7ef25fe1b62283f761655784c4ed","in_registry":true,"has_docs":true,"has_readme":true,"ci":[],"license":"BSD3","summary":"Elm interface to the Google Geocoding API","elm_versions":["0.18.0"],"exposed_modules":["Geocoding"],"direct_dependencies":{"NoRedInk/elm-decode-pipeline":"3.0.0 <= v < 4.0.0","elm-lang/core":"5.0.0 <= v < 6.0.0","elm-lang/http":"1.0.0 <= v < 2.0.0"}}}},{"version":"4.0.0","status":{"Ok":{"name":"labzero/elm-google-geocoding","datetime":"2016-11-14T21:18:11Z","checksum":"85aa977fff1111b1757faf86e7347eb586682f5c","in_registry":true,"has_docs":true,"has_readme":true,"ci":[],"license":"BSD3","summary":"Elm interface to the Google Geocoding API","elm_versions":["0.18.0"],"exposed_modules":["Geocoding"],"direct_dependencies":{"NoRedInk/elm-decode-pipeline":"3.0.0 <= v < 4.0.0","elm-lang/core":"5.0.0 <= v < 6.0.0","elm-lang/http":"1.0.0 <= v < 2.0.0"}}}},{"version":"3.0.0","status":{"Ok":{"name":"labzero/elm-google-geocoding","datetime":"2016-10-20T17:08:06Z","checksum":"3ac9f1116a636f0ab7dc942f0d6405b72094f02f","in_registry":true,"has_docs":true,"has_readme":true,"ci":[],"license":"BSD3","summary":"Elm interface to the Google Geocoding API","elm_versions":["0.17.1"],"exposed_modules":["Geocoding"],"direct_dependencies":{"NoRedInk/elm-decode-pipeline":"2.0.0 <= v < 3.0.0","elm-lang/core":"4.0.5 <= v < 5.0.0","evancz/elm-http":"3.0.1 <= v < 4.0.0"}}}},{"version":"2.0.0","status":{"Broken":{"name":"labzero/elm-google-geocoding","problems":["Git commit tag for release '2.0.0' does not match the package version '1.0.1' specified in the package JSON file. Ignoring value in the JSON file."],"datetime":"2016-10-13T16:22:04Z","checksum":"60473223f0b2e908b36a4a52ca6b43ad7927f3d9","in_registry":true,"has_docs":false,"has_readme":true,"ci":null,"license":"BSD3","summary":"Elm interface to the Google Geocoding API","elm_versions":["0.17.1"],"exposed_modules":["Geocoding"],"direct_dependencies":{"NoRedInk/elm-decode-pipeline":"2.0.0 <= v < 3.0.0","elm-lang/core":"4.0.5 <= v < 5.0.0","evancz/elm-http":"3.0.1 <= v < 4.0.0"}}}},{"version":"1.0.1","status":{"Ok":{"name":"labzero/elm-google-geocoding","datetime":"2016-10-12T16:06:39Z","checksum":"2b2d07aa3dd31d3a0d0dbf3875dd7ed2c604d452","in_registry":true,"has_docs":true,"has_readme":true,"ci":[],"license":"BSD3","summary":"Elm interface to the Google Geocoding API","elm_versions":["0.17.1"],"exposed_modules":["Geocoding"],"direct_dependencies":{"NoRedInk/elm-decode-pipeline":"2.0.0 <= v < 3.0.0","elm-lang/core":"4.0.5 <= v < 5.0.0","evancz/elm-http":"3.0.1 <= v < 4.0.0"}}}},{"version":"1.0.0","status":{"Ok":{"name":"labzero/elm-google-geocoding","datetime":"2016-10-11T23:49:17Z","checksum":"3d1d5134808b3b37102b521903e2d9258f06c1fa","in_registry":true,"has_docs":true,"has_readme":true,"ci":[],"license":"BSD3","summary":"Elm interface to the Google Geocoding API","elm_versions":["0.17.1"],"exposed_modules":["Geocoding"],"direct_dependencies":{"NoRedInk/elm-decode-pipeline":"2.0.0 <= v < 3.0.0","elm-lang/core":"4.0.5 <= v < 5.0.0","evancz/elm-http":"3.0.1 <= v < 4.0.0"}}}}]}