{"releases":[{"version":"1.1.0","status":{"Ok":{"name":"soenkehahn/elm-operational","datetime":"2017-04-02T04:10:37Z","checksum":"a84a38254a0ad6417907387657998d277c133367","in_registry":true,"has_docs":true,"has_readme":true,"ci":[],"license":"BSD3","summary":"declare elm components without using `Cmd` to facilitate testing","elm_versions":["0.18.0"],"direct_dependencies":{"elm-lang/core":"5.0.0 <= v < 6.0.0"}}}},{"version":"1.0.1","status":{"Ok":{"name":"soenkehahn/elm-operational","datetime":"2017-01-14T04:06:30Z","checksum":"7348e7ede480a04b254d13992b9e08835c7521db","in_registry":true,"has_docs":true,"has_readme":true,"ci":[],"license":"BSD3","summary":"declare elm components without using `Cmd` to facilitate testing","elm_versions":["0.18.0"],"direct_dependencies":{"elm-lang/core":"5.0.0 <= v < 6.0.0"}}}},{"version":"1.0.0","status":{"Ok":{"name":"soenkehahn/elm-operational","datetime":"2017-01-14T03:53:11Z","checksum":"37aa1247ac22c3edb55f73548a83d207c236232d","in_registry":true,"has_docs":true,"has_readme":false,"ci":[],"license":"BSD3","summary":"declare elm components without using `Cmd` to facilitate testing","elm_versions":["0.18.0"],"direct_dependencies":{"elm-lang/core":"5.0.0 <= v < 6.0.0"}}}}]}