{"releases":[{"version":"1.4.0","status":{"Ok":{"name":"fapian/elm-html-aria","datetime":"2018-08-30T06:22:30Z","checksum":"b8865fe11912151794ced7ecfd78750e2093170b","in_registry":true,"has_docs":true,"has_readme":true,"ci":[],"license":"BSD-3-Clause","summary":"Aria attributes for Elm","elm_versions":["0.19.0"],"direct_dependencies":{"elm/core":"1.0.0 <= v < 2.0.0","elm/html":"1.0.0 <= v < 2.0.0","elm/json":"1.0.0 <= v < 2.0.0"}}}},{"version":"1.3.1","status":{"Ok":{"name":"fapian/elm-html-aria","datetime":"2018-08-30T05:46:17Z","checksum":"a31e11c5dcda17288eaa4c91de212871159907ac","in_registry":true,"has_docs":true,"has_readme":true,"ci":[],"license":"BSD-3-Clause","summary":"Aria attributes for Elm","elm_versions":["0.19.0"],"direct_dependencies":{"elm/core":"1.0.0 <= v < 2.0.0","elm/html":"1.0.0 <= v < 2.0.0","elm/json":"1.0.0 <= v < 2.0.0"}}}},{"version":"1.3.0","status":{"Ok":{"name":"fapian/elm-html-aria","datetime":"2018-02-17T14:02:39Z","checksum":"8f41c3d2bce39e0259ecc3ed2454219c21833400","in_registry":true,"has_docs":true,"has_readme":true,"ci":[],"license":"BSD3","summary":"Aria attributes for Elm","elm_versions":["0.18.0"],"direct_dependencies":{"elm-lang/core":"5.0.0 <= v < 6.0.0","elm-lang/html":"2.0.0 <= v < 3.0.0"}}}},{"version":"1.2.2","status":{"Ok":{"name":"fapian/elm-html-aria","datetime":"2016-11-15T17:02:58Z","checksum":"68b0870a7d331758b51e7ddf6e0991c08fa75cb0","in_registry":true,"has_docs":true,"has_readme":true,"ci":[],"license":"BSD3","summary":"Aria attributes for elm","elm_versions":["0.18.0"],"direct_dependencies":{"elm-lang/core":"5.0.0 <= v < 6.0.0","elm-lang/html":"2.0.0 <= v < 3.0.0"}}}},{"version":"1.2.1","status":{"Ok":{"name":"fapian/elm-html-aria","datetime":"2016-09-05T16:30:51Z","checksum":"3b11cb8df640abb578c5eab0eadba602a197cd4c","in_registry":true,"has_docs":true,"has_readme":true,"ci":[],"license":"BSD3","summary":"Aria attributes for elm","elm_versions":["0.17.1","0.17.0"],"direct_dependencies":{"elm-lang/core":"4.0.1 <= v < 5.0.0","elm-lang/html":"1.1.0 <= v < 2.0.0"}}}},{"version":"1.2.0","status":{"Ok":{"name":"fapian/elm-html-aria","datetime":"2016-09-05T16:24:13Z","checksum":"991f1eb0b94579749b169c2d158f332be2b85cd6","in_registry":true,"has_docs":true,"has_readme":true,"ci":[],"license":"BSD3","summary":"Aria attributes for elm","elm_versions":["0.17.1","0.17.0"],"direct_dependencies":{"elm-lang/core":"4.0.1 <= v < 5.0.0","elm-lang/html":"1.1.0 <= v < 2.0.0"}}}},{"version":"1.1.0","status":{"Ok":{"name":"fapian/elm-html-aria","datetime":"2016-08-19T04:35:49Z","checksum":"1f08d0367b6e6843bbd18924945cd725e6e803b9","in_registry":true,"has_docs":true,"has_readme":true,"ci":[],"license":"BSD3","summary":"Aria attributes for elm","elm_versions":["0.17.1","0.17.0"],"direct_dependencies":{"elm-lang/core":"4.0.1 <= v < 5.0.0","elm-lang/html":"1.1.0 <= v < 2.0.0"}}}},{"version":"1.0.3","status":{"Ok":{"name":"fapian/elm-html-aria","datetime":"2016-08-19T04:33:35Z","checksum":"b786b30d8eb6b19dc0502bba04b328e0a1d274ca","in_registry":false,"has_docs":true,"has_readme":true,"ci":[],"license":"BSD3","summary":"Aria attributes for elm","elm_versions":["0.17.1","0.17.0"],"direct_dependencies":{"elm-lang/core":"4.0.1 <= v < 5.0.0","elm-lang/html":"1.1.0 <= v < 2.0.0"}}}},{"version":"1.0.2","status":{"Ok":{"name":"fapian/elm-html-aria","datetime":"2016-08-19T04:28:07Z","checksum":"b892e40d77c0e20d85dfa5851eb29ac79dbedbb1","in_registry":true,"has_docs":true,"has_readme":true,"ci":[],"license":"BSD3","summary":"Aria attributes for elm","elm_versions":["0.17.1","0.17.0"],"direct_dependencies":{"elm-lang/core":"4.0.1 <= v < 5.0.0","elm-lang/html":"1.1.0 <= v < 2.0.0"}}}},{"version":"1.0.1","status":{"Ok":{"name":"fapian/elm-html-aria","datetime":"2016-07-07T14:55:20Z","checksum":"0df0244a417d53faa07f5cf440a31bb3474ef8bc","in_registry":true,"has_docs":true,"has_readme":true,"ci":[],"license":"BSD3","summary":"Aria attributes for elm","elm_versions":["0.17.1","0.17.0"],"direct_dependencies":{"elm-lang/core":"4.0.1 <= v < 5.0.0","elm-lang/html":"1.1.0 <= v < 2.0.0"}}}},{"version":"1.0.0","status":{"Ok":{"name":"fapian/elm-html-aria","datetime":"2016-07-07T14:33:18Z","checksum":"f11365ce08bc0d2db9aecf4748177751ae2c74ec","in_registry":true,"has_docs":true,"has_readme":true,"ci":[],"license":"BSD3","summary":"Aria attributes for elm","elm_versions":["0.17.1","0.17.0"],"direct_dependencies":{"elm-lang/core":"4.0.1 <= v < 5.0.0","elm-lang/html":"1.1.0 <= v < 2.0.0"}}}}]}