{"releases":[{"version":"1.0.0","status":{"Ok":{"name":"deadfoxygrandpa/elm-architecture","datetime":"2016-02-25T04:43:52Z","checksum":"98ef280ba2a9d53d0df3030b6fde0151274494b6","in_registry":true,"has_docs":true,"has_readme":true,"ci":[],"license":"BSD3","summary":"Use The Elm Architecture to generate any type of Signal","elm_versions":["0.16.0","0.15.1","0.15.0"],"exposed_modules":["Architecture","Architecture.Simple"],"direct_dependencies":{"elm-lang/core":"2.0.1 <= v < 4.0.0","evancz/elm-effects":"2.0.0 <= v < 3.0.0"}}}}]}