{"releases":[{"version":"1.0.2","status":{"Ok":{"name":"elm-community/elm-time","datetime":"2017-03-01T04:32:42Z","checksum":"67fe03d7349dc834c1786956ad4e2abd8e7fca3d","in_registry":true,"has_docs":true,"has_readme":true,"ci":[],"license":"BSD3","summary":"A pure Elm date and time library.","elm_versions":["0.18.0"],"direct_dependencies":{"Bogdanp/elm-combine":"3.0.0 <= v < 4.0.0","elm-lang/core":"5.0.0 <= v < 6.0.0","elm-lang/lazy":"2.0.0 <= v < 3.0.0"}}}},{"version":"1.0.0","status":{"Ok":{"name":"isaacseymour/deprecated-time","datetime":"2018-09-06T08:49:12Z","checksum":"b6c43d525eeeb486371abada6c5d7ab6f312ffa0","in_registry":true,"has_docs":true,"has_readme":true,"ci":[],"license":"BSD-3-Clause","summary":"elm-community/elm-time updated to 0.19","elm_versions":["0.19.0"],"direct_dependencies":{"elm/core":"1.0.0 <= v < 2.0.0","elm/parser":"1.1.0 <= v < 2.0.0","elm/time":"1.0.0 <= v < 2.0.0","elm-community/list-extra":"8.0.0 <= v < 9.0.0"}}}}]}