{"releases":[{"version":"1.0.2","status":{"Ok":{"name":"allo-media/fable","datetime":"2018-11-14T14:07:43Z","checksum":"515d766b7b50f6afe04a341cebd24cd3cdc98b8b","in_registry":true,"has_docs":true,"has_readme":true,"ci":[],"license":"MIT","summary":"Want to be a real wizard, with fable you can tale some stories from you views!","elm_versions":["0.19.0"],"exposed_modules":["Fable"],"direct_dependencies":{"elm/browser":"1.0.0 <= v < 2.0.0","elm/core":"1.0.0 <= v < 2.0.0","elm/html":"1.0.0 <= v < 2.0.0","elm/url":"1.0.0 <= v < 2.0.0","rtfeldman/elm-css":"16.0.0 <= v < 17.0.0"}}}},{"version":"1.0.1","status":{"Ok":{"name":"allo-media/fable","datetime":"2018-11-12T18:17:34Z","checksum":"545a6617f8a12fb324eb5b25fa13a658f07bc320","in_registry":true,"has_docs":true,"has_readme":true,"ci":[],"license":"MIT","summary":"Create a book of your html view","elm_versions":["0.19.0"],"exposed_modules":["Fable"],"direct_dependencies":{"elm/browser":"1.0.0 <= v < 2.0.0","elm/core":"1.0.0 <= v < 2.0.0","elm/html":"1.0.0 <= v < 2.0.0","elm/url":"1.0.0 <= v < 2.0.0","rtfeldman/elm-css":"16.0.0 <= v < 17.0.0"}}}},{"version":"1.0.0","status":{"Ok":{"name":"allo-media/fable","datetime":"2018-10-19T08:50:57Z","checksum":"41d5cc434e73d382342f959c8d682639d5468215","in_registry":true,"has_docs":true,"has_readme":true,"ci":[],"license":"MIT","summary":"Create a book of your html view","elm_versions":["0.19.0"],"exposed_modules":["Fable"],"direct_dependencies":{"elm/browser":"1.0.0 <= v < 2.0.0","elm/core":"1.0.0 <= v < 2.0.0","elm/html":"1.0.0 <= v < 2.0.0","elm/url":"1.0.0 <= v < 2.0.0","rtfeldman/elm-css":"15.1.0 <= v < 16.0.0"}}}}]}